[
    {
        "is_live": true,
        "date": "2025-08-04T11:00:00Z",
        "time": "",
        "id": "9912050",
        "logo": "",
        "home_team": "Daegu FC",
        "home_image": "https:\/\/sta.vnres.co\/file\/common\/20250801\/99fcc51e589addff0dc7c595ab4660a7.png",
        "away_team": "FC Barcelona",
        "away_image": "https:\/\/sta.vnres.co\/file\/common\/20250801\/d8974fcabed603efeb1e9eba1b49aae6.png",
        "league": "INT CF",
        "links": [
            {
                "title": "Soco SD",
                "url": "https:\/\/pull.niur.live\/live\/stream-414317_lsd.m3u8?txSecret=0ba7756e16b916a2075057e704c060f1&txTime=68910323",
                "referrer": "https:\/\/socolivev.co\/",
                "user_agent": ""
            },
            {
                "title": "Soco HD",
                "url": "https:\/\/pull.niur.live\/live\/stream-414317_lhd.m3u8?txSecret=3d80a2361950d7465d9660c562f879c8&txTime=68910323",
                "referrer": "https:\/\/socolivev.co\/",
                "user_agent": ""
            },
            {
                "title": "Soco SD",
                "url": "https:\/\/pull.niur.live\/live\/stream-9912041_lsd.m3u8?txSecret=c6b37c4e103e98034fcaa11fe50007f7&txTime=68910330",
                "referrer": "https:\/\/socolivev.co\/",
                "user_agent": ""
            },
            {
                "title": "Soco HD",
                "url": "https:\/\/pull.niur.live\/live\/stream-9912041_lhd.m3u8?txSecret=dcff92cfbf81426c13c3edb3771a0ef1&txTime=68910330",
                "referrer": "https:\/\/socolivev.co\/",
                "user_agent": ""
            },
            {
                "title": "Soco SD",
                "url": "https:\/\/pull.niues.live\/live\/stream-494201_lsd.m3u8?auth_key=1754315987-0-0-84227beb24b490f1346996749e75faa7",
                "referrer": "https:\/\/socolivev.co\/",
                "user_agent": ""
            },
            {
                "title": "Soco HD",
                "url": "https:\/\/pull.niues.live\/live\/stream-494201_lhd.m3u8?auth_key=1754315987-0-0-2412b1cc6c3aba8d97d06c334363a6fe",
                "referrer": "https:\/\/socolivev.co\/",
                "user_agent": ""
            },
            {
                "title": "Soco SD",
                "url": "https:\/\/pull.niur.live\/live\/stream-9912103_lsd.m3u8?txSecret=c1157edf0c69750711ab2bfcf2b62f0f&txTime=68910323",
                "referrer": "https:\/\/socolivev.co\/",
                "user_agent": ""
            },
            {
                "title": "Soco HD",
                "url": "https:\/\/pull.niur.live\/live\/stream-9912103_lhd.m3u8?txSecret=ceb41ce04ed4814136c2ffad96180387&txTime=68910323",
                "referrer": "https:\/\/socolivev.co\/",
                "user_agent": ""
            },
            {
                "title": "Soco SD",
                "url": "https:\/\/pull.niues.live\/live\/stream-327159_lsd.m3u8?auth_key=1754315987-0-0-c168bdd4a73fc4a72d21dfcafb4e1df0",
                "referrer": "https:\/\/socolivev.co\/",
                "user_agent": ""
            },
            {
                "title": "Soco HD",
                "url": "https:\/\/pull.niues.live\/live\/stream-327159_lhd.m3u8?auth_key=1754315987-0-0-18dc7473817b9e0d16060695805efb23",
                "referrer": "https:\/\/socolivev.co\/",
                "user_agent": ""
            },
            {
                "title": "Soco SD",
                "url": "https:\/\/pull.niur.live\/live\/stream-9912050_lsd.m3u8?txSecret=97a4e3f2f9fdba71dc340c525152e362&txTime=68910323",
                "referrer": "https:\/\/socolivev.co\/",
                "user_agent": ""
            },
            {
                "title": "Soco HD",
                "url": "https:\/\/pull.niur.live\/live\/stream-9912050_lhd.m3u8?txSecret=1d534a57342f2c46e5db7c0c6b37ad7f&txTime=68910323",
                "referrer": "https:\/\/socolivev.co\/",
                "user_agent": ""
            }
        ]
    },
    {
        "is_live": true,
        "date": "2025-08-04T11:30:00Z",
        "time": "",
        "id": "428392",
        "logo": "",
        "home_team": "Jiangxi Ganchi",
        "home_image": "https:\/\/sta.vnres.co\/file\/common\/20250802\/187535b25579ce211d6fde6ed99b5f11.png",
        "away_team": "Hubei Wenlv",
        "away_image": "https:\/\/sta.vnres.co\/file\/common\/20250802\/995cb08228aa8575414532e90c66160b.png",
        "league": "CNBL",
        "links": [
            {
                "title": "Soco SD",
                "url": "https:\/\/stream-flv.dfsfe.top\/lives\/428392-480p.m3u8",
                "referrer": "https:\/\/socolivev.co\/",
                "user_agent": ""
            },
            {
                "title": "Soco HD",
                "url": "https:\/\/stream-flv.dfsfe.top\/lives\/428392-720p.m3u8",
                "referrer": "https:\/\/socolivev.co\/",
                "user_agent": ""
            }
        ]
    },
    {
        "is_live": true,
        "date": "2025-08-04T12:00:00Z",
        "time": "",
        "id": "9912107",
        "logo": "",
        "home_team": "San Juan Knights",
        "home_image": "https:\/\/sta.vnres.co\/file\/common\/20250802\/d760395f223f81e47260162d15d08d2a.png",
        "away_team": "Zamboanga Sikat",
        "away_image": "https:\/\/sta.vnres.co\/file\/common\/20250802\/5ff889e4b0a69d9a798c5a23424a568d.png",
        "league": "MPBL",
        "links": [
            {
                "title": "Soco SD",
                "url": "https:\/\/pull.niur.live\/live\/stream-9912107_lsd.m3u8?txSecret=ab15c303e4acfea781794e8fee654a75&txTime=68910323",
                "referrer": "https:\/\/socolivev.co\/",
                "user_agent": ""
            },
            {
                "title": "Soco HD",
                "url": "https:\/\/pull.niur.live\/live\/stream-9912107_lhd.m3u8?txSecret=3d54ed04f2ac7c8a43424ac8d03f2126&txTime=68910323",
                "referrer": "https:\/\/socolivev.co\/",
                "user_agent": ""
            }
        ]
    },
    {
        "is_live": false,
        "date": "2025-08-04T13:30:00Z",
        "time": "",
        "id": "9912107",
        "logo": "",
        "home_team": "Alashkert",
        "home_image": "https:\/\/sta.vnres.co\/file\/common\/20250801\/d4a6556e866475d32aa2a599aa9663df.png",
        "away_team": "FC Pyunik",
        "away_image": "https:\/\/sta.vnres.co\/file\/common\/20250801\/145d96614b3ceca7039cddc65f440bcf.png",
        "league": "ARM D1",
        "links": []
    },
    {
        "is_live": false,
        "date": "2025-08-04T13:30:00Z",
        "time": "",
        "id": "9912107",
        "logo": "",
        "home_team": "FK Van Charentsavan",
        "home_image": "https:\/\/sta.vnres.co\/file\/common\/20250801\/934545d99f5be37d6cd6ddb2a4b90562.png",
        "away_team": "Ararat-Armenia FC",
        "away_image": "https:\/\/sta.vnres.co\/file\/common\/20250801\/dcdbb8322155d4ad102ce818f4e1e033.png",
        "league": "ARM D1",
        "links": []
    },
    {
        "is_live": false,
        "date": "2025-08-04T14:00:00Z",
        "time": "",
        "id": "9912107",
        "logo": "",
        "home_team": "Niger",
        "home_image": "https:\/\/sta.vnres.co\/file\/common\/20250801\/9898c85e96b82f2e0e898bdabea22d21.png",
        "away_team": "Guinea",
        "away_image": "https:\/\/sta.vnres.co\/file\/common\/20250801\/f94da11c016a77a95dbddf5633a16e3c.png",
        "league": "CAF CHAN",
        "links": []
    },
    {
        "is_live": false,
        "date": "2025-08-04T15:00:00Z",
        "time": "",
        "id": "9912107",
        "logo": "",
        "home_team": "Ilves Tampere",
        "home_image": "https:\/\/sta.vnres.co\/file\/common\/20250801\/90e8c124d6d416d4454984499f87ec93.png",
        "away_team": "Gnistan Helsinki",
        "away_image": "https:\/\/sta.vnres.co\/file\/common\/20250801\/5c7534aa9331a2d45c3fb095bc9ee36a.png",
        "league": "FIN D1",
        "links": []
    },
    {
        "is_live": false,
        "date": "2025-08-04T15:00:00Z",
        "time": "",
        "id": "9912107",
        "logo": "",
        "home_team": "Metalist 1925 Kharkiv",
        "home_image": "https:\/\/sta.vnres.co\/file\/common\/20250801\/64bd24c4eef17d179e2d5791cc6626d7.png",
        "away_team": "Obolon Kyiv",
        "away_image": "https:\/\/sta.vnres.co\/file\/common\/20250801\/c4be2fcf05ac54c8cf857c68c826e532.png",
        "league": "UKR D1",
        "links": []
    },
    {
        "is_live": false,
        "date": "2025-08-04T16:00:00Z",
        "time": "",
        "id": null,
        "logo": "",
        "home_team": "Liverpool",
        "home_image": "https:\/\/sta.vnres.co\/file\/common\/20250801\/820839017820967dd548a5ea39174113.png",
        "away_team": "Athletic Club",
        "away_image": "https:\/\/sta.vnres.co\/file\/common\/20250801\/9b4522add47ff769910189d1eb0bf9e2.png",
        "league": "INT CF",
        "links": []
    },
    {
        "is_live": false,
        "date": "2025-08-04T16:00:00Z",
        "time": "",
        "id": null,
        "logo": "",
        "home_team": "HJK Helsinki",
        "home_image": "https:\/\/sta.vnres.co\/file\/common\/20250801\/faa9c8591821372481206268e9e082d8.png",
        "away_team": "Inter Turku",
        "away_image": "https:\/\/sta.vnres.co\/file\/common\/20250801\/6f46debcbb5f25cb8505c97cba18aeb2.png",
        "league": "FIN D1",
        "links": []
    },
    {
        "is_live": false,
        "date": "2025-08-04T16:00:00Z",
        "time": "",
        "id": null,
        "logo": "",
        "home_team": "FC Unirea 2004 Slobozia",
        "home_image": "https:\/\/sta.vnres.co\/file\/common\/20250801\/16d22b878826ab17ecef319406511c8f.png",
        "away_team": "FC Otelul Galati",
        "away_image": "https:\/\/sta.vnres.co\/file\/common\/20250801\/f7e180ae17728be7f28aa9a87e639de2.png",
        "league": "ROM D1",
        "links": []
    },
    {
        "is_live": false,
        "date": "2025-08-04T16:00:00Z",
        "time": "",
        "id": null,
        "logo": "",
        "home_team": "Cherno More Varna",
        "home_image": "https:\/\/sta.vnres.co\/file\/common\/20250801\/b8c5321ccffef602a158f696356be2d4.png",
        "away_team": "Beroe Stara Zagora",
        "away_image": "https:\/\/sta.vnres.co\/file\/common\/20250801\/b5fe4fb6cc74bd2c068345fdd3418fe5.png",
        "league": "BUL D1",
        "links": []
    },
    {
        "is_live": false,
        "date": "2025-08-04T16:00:00Z",
        "time": "",
        "id": null,
        "logo": "",
        "home_team": "Banga Gargzdai",
        "home_image": "https:\/\/sta.vnres.co\/file\/common\/20250801\/563a36e83855fb73d9cef77b6ec6e3b8.png",
        "away_team": "Siauliai",
        "away_image": "https:\/\/sta.vnres.co\/file\/common\/20250801\/93ae8da4ab7693eb2b1d593d82653260.png",
        "league": "LIT D1",
        "links": []
    },
    {
        "is_live": false,
        "date": "2025-08-04T16:30:00Z",
        "time": "",
        "id": null,
        "logo": "",
        "home_team": "Dziugas Telsiai",
        "home_image": "https:\/\/sta.vnres.co\/file\/common\/20250801\/739aebbb915c23759b11a4c0c2716ae5.png",
        "away_team": "Hegelmann Litauen",
        "away_image": "https:\/\/sta.vnres.co\/file\/common\/20250801\/b4de963d846055300fa5cb1af39d506c.png",
        "league": "LIT D1",
        "links": []
    },
    {
        "is_live": false,
        "date": "2025-08-04T17:00:00Z",
        "time": "",
        "id": null,
        "logo": "",
        "home_team": "IFK Goteborg",
        "home_image": "https:\/\/sta.vnres.co\/file\/common\/20250802\/6325262445338895455fefb548dfbb7f.png",
        "away_team": "Degerfors IF",
        "away_image": "https:\/\/sta.vnres.co\/file\/common\/20250802\/85371363510609d8901943236b4cc011.png",
        "league": "SWE D1",
        "links": []
    },
    {
        "is_live": false,
        "date": "2025-08-04T17:00:00Z",
        "time": "",
        "id": null,
        "logo": "",
        "home_team": "Rubin Kazan",
        "home_image": "https:\/\/sta.vnres.co\/file\/common\/20250802\/357225f2a9c9f7e55c300710b76aca82.png",
        "away_team": "FC Sochi",
        "away_image": "https:\/\/sta.vnres.co\/file\/common\/20250802\/304314a6a60954ddaae71d0619dbed1c.png",
        "league": "RUS D1",
        "links": []
    },
    {
        "is_live": false,
        "date": "2025-08-04T17:00:00Z",
        "time": "",
        "id": null,
        "logo": "",
        "home_team": "Novi Pazar",
        "home_image": "https:\/\/sta.vnres.co\/file\/common\/20250802\/03d9ccfb833e829fbec367b995e9d0b8.png",
        "away_team": "FK IMT Belgrad",
        "away_image": "https:\/\/sta.vnres.co\/file\/common\/20250802\/4e7e7b431c790d14970cfa6df8b1c207.png",
        "league": "SER SL",
        "links": []
    },
    {
        "is_live": false,
        "date": "2025-08-04T17:00:00Z",
        "time": "",
        "id": null,
        "logo": "",
        "home_team": "Uganda",
        "home_image": "https:\/\/sta.vnres.co\/file\/common\/20250802\/3f062b4187989ed42648fe0db24851a1.png",
        "away_team": "Algeria",
        "away_image": "https:\/\/sta.vnres.co\/file\/common\/20250802\/bf9507278c74054f589c23a96e0c2047.png",
        "league": "CAF CHAN",
        "links": []
    },
    {
        "is_live": false,
        "date": "2025-08-04T17:00:00Z",
        "time": "",
        "id": null,
        "logo": "",
        "home_team": "FK Zeleznicar Pancevo",
        "home_image": "https:\/\/sta.vnres.co\/file\/common\/20250802\/b48976edeca8d980ac352ac9bb80f4ec.png",
        "away_team": "FK Napredak Krusevac",
        "away_image": "https:\/\/sta.vnres.co\/file\/common\/20250802\/fbe008967d70218aeac214348a874453.png",
        "league": "SER SL",
        "links": []
    },
    {
        "is_live": false,
        "date": "2025-08-04T18:00:00Z",
        "time": "",
        "id": null,
        "logo": "",
        "home_team": "NK Varazdin",
        "home_image": "https:\/\/sta.vnres.co\/file\/common\/20250802\/d44c67979b4dd29d17d9da8702da5878.png",
        "away_team": "HNK Gorica",
        "away_image": "https:\/\/sta.vnres.co\/file\/common\/20250802\/7a67fab50324d75ee0206c44fdcc02e3.png",
        "league": "CRO D1",
        "links": []
    },
    {
        "is_live": false,
        "date": "2025-08-04T18:15:00Z",
        "time": "",
        "id": null,
        "logo": "",
        "home_team": "Botev Plovdiv",
        "home_image": "https:\/\/sta.vnres.co\/file\/common\/20250802\/ef9f34313f65e808284d525c86cd5082.png",
        "away_team": "Arda",
        "away_image": "https:\/\/sta.vnres.co\/file\/common\/20250802\/a4d93baf4ee7b156616409c5d280f8cf.png",
        "league": "BUL D1",
        "links": []
    },
    {
        "is_live": false,
        "date": "2025-08-04T18:30:00Z",
        "time": "",
        "id": null,
        "logo": "",
        "home_team": "FC Rapid 1923",
        "home_image": "https:\/\/sta.vnres.co\/file\/common\/20250802\/96e7b354ed66ebf23329aecc2f06e48d.png",
        "away_team": "FC Botosani",
        "away_image": "https:\/\/sta.vnres.co\/file\/common\/20250802\/a0237d88cb616c01de728aebe29cd75f.png",
        "league": "ROM D1",
        "links": []
    },
    {
        "is_live": false,
        "date": "2025-08-04T19:00:00Z",
        "time": "",
        "id": null,
        "logo": "",
        "home_team": "Heart of Midlothian",
        "home_image": "https:\/\/sta.vnres.co\/file\/common\/20250802\/9913ed5423f5e7851f4fc6dea4019c1e.png",
        "away_team": "Aberdeen",
        "away_image": "https:\/\/sta.vnres.co\/file\/common\/20250802\/eadef1f69188a2c43c722a498b7e8911.png",
        "league": "SCO PR",
        "links": []
    },
    {
        "is_live": false,
        "date": "2025-08-04T19:00:00Z",
        "time": "",
        "id": null,
        "logo": "",
        "home_team": "Liverpool",
        "home_image": "https:\/\/sta.vnres.co\/file\/common\/20250804\/57ce49aef0b3742b9998d239bc665298.png",
        "away_team": "Athletic Club",
        "away_image": "https:\/\/sta.vnres.co\/file\/common\/20250804\/0d7d3c208e856cdf3160857854d21fff.png",
        "league": "INT CF",
        "links": []
    },
    {
        "is_live": false,
        "date": "2025-08-04T19:00:00Z",
        "time": "",
        "id": null,
        "logo": "",
        "home_team": "Sevilla FC",
        "home_image": "https:\/\/sta.vnres.co\/file\/common\/20250804\/025fc64a9054d1da1ef09f7856c3423f.png",
        "away_team": "Al Qadisiya",
        "away_image": "https:\/\/sta.vnres.co\/file\/common\/20250804\/53976ae2ee54cf03d6ae7513f4c009f2.png",
        "league": "INT CF",
        "links": []
    },
    {
        "is_live": false,
        "date": "2025-08-04T20:00:00Z",
        "time": "",
        "id": null,
        "logo": "",
        "home_team": "Sport Boys",
        "home_image": "https:\/\/sta.vnres.co\/file\/common\/20250802\/4df335d1136ec72f46d6c18555ddfa51.png",
        "away_team": "AD Tarma",
        "away_image": "https:\/\/sta.vnres.co\/file\/common\/20250802\/78e0d55085e7e3e4a06424377642947d.png",
        "league": "PER D1",
        "links": []
    },
    {
        "is_live": false,
        "date": "2025-08-04T21:30:00Z",
        "time": "",
        "id": null,
        "logo": "",
        "home_team": "Deportivo Recoleta",
        "home_image": "https:\/\/sta.vnres.co\/file\/common\/20250802\/6a3c6ecf9d0eee4b1f83d2ff0de902b8.png",
        "away_team": "Club Guaran\u00ed",
        "away_image": "https:\/\/sta.vnres.co\/file\/common\/20250802\/8afa110801fb6ae2254d94b3c44ebaae.png",
        "league": "PAR D1",
        "links": []
    },
    {
        "is_live": false,
        "date": "2025-08-04T21:30:00Z",
        "time": "",
        "id": null,
        "logo": "",
        "home_team": "Always Ready",
        "home_image": "https:\/\/sta.vnres.co\/file\/common\/20250803\/ae7370b944d76761981daebd721453b9.png",
        "away_team": "Nacional Potosi",
        "away_image": "https:\/\/sta.vnres.co\/file\/common\/20250803\/101ad7381087d52d0adf1f0d4bde2894.png",
        "league": "BOL D1",
        "links": []
    },
    {
        "is_live": false,
        "date": "2025-08-04T22:00:00Z",
        "time": "",
        "id": null,
        "logo": "",
        "home_team": "Universidad de Chile",
        "home_image": "https:\/\/sta.vnres.co\/file\/common\/20250802\/bd6dede95e01a3df7b5bd9fb5b95b945.png",
        "away_team": "Cobresal",
        "away_image": "https:\/\/sta.vnres.co\/file\/common\/20250802\/209f271a5f1e4ac9518d0268bdcd9bcc.png",
        "league": "CHI D1",
        "links": []
    },
    {
        "is_live": false,
        "date": "2025-08-04T22:00:00Z",
        "time": "",
        "id": null,
        "logo": "",
        "home_team": "Athletic Club MG",
        "home_image": "https:\/\/sta.vnres.co\/file\/common\/20250802\/735be17d3a5434e261353da3288ebcc5.png",
        "away_team": "Atletico Clube Goianiense",
        "away_image": "https:\/\/sta.vnres.co\/file\/common\/20250802\/5400b556740cb0979c0eb44322081a17.png",
        "league": "BRA D2",
        "links": []
    },
    {
        "is_live": false,
        "date": "2025-08-04T23:00:00Z",
        "time": "",
        "id": null,
        "logo": "",
        "home_team": "Santos",
        "home_image": "https:\/\/sta.vnres.co\/file\/common\/20250802\/ce079411300934dc57afe4013ffa8774.png",
        "away_team": "Juventude",
        "away_image": "https:\/\/sta.vnres.co\/file\/common\/20250802\/dc91dff39780f37b24d9c7512cc4f187.png",
        "league": "BRA D1",
        "links": []
    },
    {
        "is_live": false,
        "date": "2025-08-04T23:00:00Z",
        "time": "",
        "id": null,
        "logo": "",
        "home_team": "Saint Louis Athletica (w)",
        "home_image": "https:\/\/sta.vnres.co\/file\/common\/20250802\/bfcfea2d7d6af6526791a557e9680f5a.png",
        "away_team": "Juarez FC (w)",
        "away_image": "https:\/\/sta.vnres.co\/file\/common\/20250802\/9165e7fb9590db9b48a807088fb901c5.png",
        "league": "MEX WD1",
        "links": []
    },
    {
        "is_live": false,
        "date": "2025-08-04T23:00:00Z",
        "time": "",
        "id": null,
        "logo": "",
        "home_team": "Unam Pumas (w)",
        "home_image": "https:\/\/sta.vnres.co\/file\/common\/20250802\/bad9c59682a645b3910415753aee05bf.png",
        "away_team": "Cruz Azul (w)",
        "away_image": "https:\/\/sta.vnres.co\/file\/common\/20250802\/486ed3ddb3937c6d8f3c8c7e4db4a55e.png",
        "league": "MEX WD1",
        "links": []
    },
    {
        "is_live": false,
        "date": "2025-08-05T00:00:00Z",
        "time": "",
        "id": null,
        "logo": "",
        "home_team": "Cienciano",
        "home_image": "https:\/\/sta.vnres.co\/file\/common\/20250802\/61dba83c6b5201a0b651bc7efaa59bc2.png",
        "away_team": "Los Chankas",
        "away_image": "https:\/\/sta.vnres.co\/file\/common\/20250802\/7bfc46b6294d1b6a6a3a3c7b447cb171.png",
        "league": "PER D1",
        "links": []
    },
    {
        "is_live": false,
        "date": "2025-08-05T00:10:00Z",
        "time": "",
        "id": null,
        "logo": "",
        "home_team": "Defensores de Belgrano",
        "home_image": "https:\/\/sta.vnres.co\/file\/common\/20250802\/2645123a722580bdc6585aad9b5cb927.png",
        "away_team": "Deportivo Moron",
        "away_image": "https:\/\/sta.vnres.co\/file\/common\/20250802\/fb30ab68ef67abca46c988307d58b054.png",
        "league": "ARG D2",
        "links": []
    },
    {
        "is_live": false,
        "date": "2025-08-05T00:30:00Z",
        "time": "",
        "id": null,
        "logo": "",
        "home_team": "Cuiaba",
        "home_image": "https:\/\/sta.vnres.co\/file\/common\/20250802\/5f84c83a6dad412b471156b5e7ddc566.png",
        "away_team": "Volta Redonda",
        "away_image": "https:\/\/sta.vnres.co\/file\/common\/20250802\/49b08db1eddc06c67f696a4e36e1ebdf.png",
        "league": "BRA D2",
        "links": []
    },
    {
        "is_live": false,
        "date": "2025-08-05T01:00:00Z",
        "time": "",
        "id": null,
        "logo": "",
        "home_team": "Pachuca (w)",
        "home_image": "https:\/\/sta.vnres.co\/file\/common\/20250802\/b0d1aa8954676cf3ec3a185e3cfea508.png",
        "away_team": "Toluca (w)",
        "away_image": "https:\/\/sta.vnres.co\/file\/common\/20250802\/3a7c44be04736da20cb2a84b683e5b21.png",
        "league": "MEX WD1",
        "links": []
    },
    {
        "is_live": false,
        "date": "2025-08-05T01:00:00Z",
        "time": "",
        "id": null,
        "logo": "",
        "home_team": "Santos Laguna (w)",
        "home_image": "https:\/\/sta.vnres.co\/file\/common\/20250802\/89c813b01cdd35d7dfafb5473080dfeb.png",
        "away_team": "Chivas Guadalajara (w)",
        "away_image": "https:\/\/sta.vnres.co\/file\/common\/20250802\/cd8d8216f9d47c0157913c77f194efe7.png",
        "league": "MEX WD1",
        "links": []
    },
    {
        "is_live": false,
        "date": "2025-08-05T01:10:00Z",
        "time": "",
        "id": null,
        "logo": "",
        "home_team": "Real Cartagena",
        "home_image": "https:\/\/sta.vnres.co\/file\/common\/20250802\/2286b108fdd8bf4e3889ef0d26d52c9f.png",
        "away_team": "Real Soacha Cundinamarca",
        "away_image": "https:\/\/sta.vnres.co\/file\/common\/20250802\/e06bb9358c6050f2cb8e8122df95d2da.png",
        "league": "COL D2",
        "links": []
    },
    {
        "is_live": false,
        "date": "2025-08-05T02:00:00Z",
        "time": "",
        "id": null,
        "logo": "",
        "home_team": "Abejas",
        "home_image": "https:\/\/sta.vnres.co\/file\/common\/20250803\/6cad39e1c8529436e6b807758a47808f.png",
        "away_team": "Dorados",
        "away_image": "https:\/\/sta.vnres.co\/file\/common\/20250803\/b2bf8728ae57ea66a67c59431f0dc8af.png",
        "league": "LNBP",
        "links": []
    },
    {
        "is_live": false,
        "date": "2025-08-05T08:00:00Z",
        "time": "",
        "id": null,
        "logo": "",
        "home_team": "New Zealand",
        "home_image": "https:\/\/sta.vnres.co\/file\/common\/20250803\/32c35d2ed82bd8ef2399105d880c70cd.png",
        "away_team": "Iraq",
        "away_image": "https:\/\/sta.vnres.co\/file\/common\/20250803\/cb09a83c79e8e141753edee39ccfd4c9.png",
        "league": "ACQ",
        "links": []
    },
    {
        "is_live": false,
        "date": "2025-08-05T08:00:00Z",
        "time": "",
        "id": null,
        "logo": "",
        "home_team": "Nueva Ecija Vanguards",
        "home_image": "https:\/\/sta.vnres.co\/file\/common\/20250803\/ee5c4148cb2d3c31fc3fadf76b9cac62.png",
        "away_team": "Pasig City",
        "away_image": "https:\/\/sta.vnres.co\/file\/common\/20250803\/7b3befc20e97bc3f6aa1c05e05be8a07.png",
        "league": "MPBL",
        "links": []
    },
    {
        "is_live": false,
        "date": "2025-08-05T09:00:00Z",
        "time": "",
        "id": null,
        "logo": "",
        "home_team": "Pakhtakor",
        "home_image": "https:\/\/sta.vnres.co\/file\/common\/20250802\/20630c68b8c176ea92929ea24c2df96b.png",
        "away_team": "FC OKMK Olmaliq",
        "away_image": "https:\/\/sta.vnres.co\/file\/common\/20250802\/cade2fa6673801e56c1530fe767879e1.png",
        "league": "UZB PFL",
        "links": []
    },
    {
        "is_live": false,
        "date": "2025-08-05T09:45:00Z",
        "time": "",
        "id": null,
        "logo": "",
        "home_team": "Sunshine Coast Wanderers FC",
        "home_image": "https:\/\/sta.vnres.co\/file\/common\/20250509\/87ce065406883a8b08577e9a16e79dda.png",
        "away_team": "Eastern Suburbs Brisbane",
        "away_image": "https:\/\/sta.vnres.co\/file\/common\/20250509\/c479af58c7af001cfbb7687bc3425391.png",
        "league": "AUS NPLQ",
        "links": []
    },
    {
        "is_live": false,
        "date": "2025-08-05T10:00:00Z",
        "time": "",
        "id": null,
        "logo": "",
        "home_team": "Muntinlupa Cagers",
        "home_image": "https:\/\/sta.vnres.co\/file\/common\/20250803\/850f2d1eec64c0b4687b389933669db4.png",
        "away_team": "Batangas City",
        "away_image": "https:\/\/sta.vnres.co\/file\/common\/20250803\/edf608505fcaea00b5e9e5a32a22f586.png",
        "league": "MPBL",
        "links": []
    },
    {
        "is_live": false,
        "date": "2025-08-05T11:00:00Z",
        "time": "",
        "id": null,
        "logo": "",
        "home_team": "Jordan",
        "home_image": "https:\/\/sta.vnres.co\/file\/common\/20250803\/dac00e81ef4a45d4993b9d2bd542df97.png",
        "away_team": "India",
        "away_image": "https:\/\/sta.vnres.co\/file\/common\/20250803\/a2ea3d55614c8b084e265ed468f39ed7.png",
        "league": "ACQ",
        "links": []
    },
    {
        "is_live": false,
        "date": "2025-08-05T12:00:00Z",
        "time": "",
        "id": null,
        "logo": "",
        "home_team": "Bataan Risers",
        "home_image": "https:\/\/sta.vnres.co\/file\/common\/20250803\/c7c168e3b13d24d155ce3f1348dc4aeb.png",
        "away_team": "Binan Tatak Gel",
        "away_image": "https:\/\/sta.vnres.co\/file\/common\/20250803\/e8e5de3be3e24b85425ecaa9119b79bb.png",
        "league": "MPBL",
        "links": []
    },
    {
        "is_live": false,
        "date": "2025-08-05T13:00:00Z",
        "time": "",
        "id": null,
        "logo": "",
        "home_team": "RW Challenge",
        "home_image": "https:\/\/sta.vnres.co\/file\/common\/20250803\/65549c7fcbe0cdcd13d78643f37c5296.png",
        "away_team": "Zvezda Sint Petersburg",
        "away_image": "https:\/\/sta.vnres.co\/file\/common\/20250803\/e62f27759daf87f5f2426ccae5469770.png",
        "league": "RUS CUP",
        "links": []
    },
    {
        "is_live": false,
        "date": "2025-08-05T14:00:00Z",
        "time": "",
        "id": null,
        "logo": "",
        "home_team": "Republic of the Congo",
        "home_image": "https:\/\/sta.vnres.co\/file\/common\/20250802\/c76865801203806209617af2e078f1b5.png",
        "away_team": "Sudan",
        "away_image": "https:\/\/sta.vnres.co\/file\/common\/20250802\/3ba6d2046dcd52536bbdd9a630776eea.png",
        "league": "CAF CHAN",
        "links": []
    },
    {
        "is_live": false,
        "date": "2025-08-05T15:00:00Z",
        "time": "",
        "id": null,
        "logo": "",
        "home_team": "FC Hebar Pazardzhik",
        "home_image": "https:\/\/sta.vnres.co\/file\/common\/20250802\/8fd4ca6e566e5dfdca0f1b38d8476623.png",
        "away_team": "Fratria",
        "away_image": "https:\/\/sta.vnres.co\/file\/common\/20250802\/04ebb50c9156df7e656f350acb26b757.png",
        "league": "BUL D2",
        "links": []
    }
]