[
    {
        "is_live": true,
        "date": "2025-07-23T15:30:00Z",
        "time": "",
        "id": "400722",
        "logo": "",
        "home_team": "Klubi 04 Helsinki",
        "home_image": "https:\/\/sta.vnres.co\/file\/common\/20250720\/158841176d81b024e33de5017d7138c1.png",
        "away_team": "Salon Palloilijat",
        "away_image": "https:\/\/sta.vnres.co\/file\/common\/20250720\/b8ea362595cb069c7ccec9b6e43e9bbe.png",
        "league": "FIN D2",
        "links": [
            {
                "title": "Soco SD",
                "url": "https:\/\/pull.niues.live\/live\/stream-494201_lsd.m3u8?auth_key=1753306203-0-0-59e3757fc6306a2fc4c7aa8491ad3cd2",
                "referrer": "https:\/\/socolivev.co\/",
                "user_agent": ""
            },
            {
                "title": "Soco HD",
                "url": "https:\/\/pull.niues.live\/live\/stream-494201_lhd.m3u8?auth_key=1753306203-0-0-69fd3746255255c43d1ae7ddd59a1f56",
                "referrer": "https:\/\/socolivev.co\/",
                "user_agent": ""
            },
            {
                "title": "Soco SD",
                "url": "https:\/\/pull.niues.live\/live\/stream-9912101_lsd.m3u8?auth_key=1753295416-0-0-a3601adb67902a3ee1da815324cf0508",
                "referrer": "https:\/\/socolivev.co\/",
                "user_agent": ""
            },
            {
                "title": "Soco HD",
                "url": "https:\/\/pull.niues.live\/live\/stream-9912101_lhd.m3u8?auth_key=1753295416-0-0-2ec7d56c231a20112dd4f389f7b93222",
                "referrer": "https:\/\/socolivev.co\/",
                "user_agent": ""
            },
            {
                "title": "Soco SD",
                "url": "https:\/\/pull.niues.live\/live\/stream-9912091_lsd.m3u8?auth_key=1753295499-0-0-6666c6c2aa1397aa86fd3e05f65d2d3b",
                "referrer": "https:\/\/socolivev.co\/",
                "user_agent": ""
            },
            {
                "title": "Soco HD",
                "url": "https:\/\/pull.niues.live\/live\/stream-9912091_lhd.m3u8?auth_key=1753295499-0-0-77a6e426a7a3f6eadd4c8fa0c5c2c201",
                "referrer": "https:\/\/socolivev.co\/",
                "user_agent": ""
            },
            {
                "title": "Soco SD",
                "url": "https:\/\/pull.niues.live\/live\/stream-400722_lsd.m3u8?auth_key=1753306203-0-0-37e209efbab3da76954906cbc6d528dd",
                "referrer": "https:\/\/socolivev.co\/",
                "user_agent": ""
            },
            {
                "title": "Soco HD",
                "url": "https:\/\/pull.niues.live\/live\/stream-400722_lhd.m3u8?auth_key=1753306203-0-0-d397564bfe90ef3e99d424104975cdbf",
                "referrer": "https:\/\/socolivev.co\/",
                "user_agent": ""
            }
        ]
    },
    {
        "is_live": true,
        "date": "2025-07-23T15:30:00Z",
        "time": "",
        "id": "9912060",
        "logo": "",
        "home_team": "Zira FK",
        "home_image": "https:\/\/sta.vnres.co\/file\/common\/20250720\/5ac9305a085c1e5f9ba80deb8d0a8026.png",
        "away_team": "Hajduk Split",
        "away_image": "https:\/\/sta.vnres.co\/file\/common\/20250720\/c36375e9cab38132aae83fa7d454f0a7.png",
        "league": "UEFA ECL",
        "links": [
            {
                "title": "Soco SD",
                "url": "https:\/\/pull.niur.live\/live\/stream-9912103_lsd.m3u8?txSecret=0c8780856bbe8b1bd81d356e8b31f692&txTime=68817077",
                "referrer": "https:\/\/socolivev.co\/",
                "user_agent": ""
            },
            {
                "title": "Soco HD",
                "url": "https:\/\/pull.niur.live\/live\/stream-9912103_lhd.m3u8?txSecret=ea1168915ef5971f070e8d3fe7e1c27a&txTime=68817077",
                "referrer": "https:\/\/socolivev.co\/",
                "user_agent": ""
            },
            {
                "title": "Soco SD",
                "url": "https:\/\/stream-flv.dfsfe.top\/lives\/9912105-480p.m3u8",
                "referrer": "https:\/\/socolivev.co\/",
                "user_agent": ""
            },
            {
                "title": "Soco HD",
                "url": "https:\/\/stream-flv.dfsfe.top\/lives\/9912105-720p.m3u8",
                "referrer": "https:\/\/socolivev.co\/",
                "user_agent": ""
            },
            {
                "title": "Soco SD",
                "url": "https:\/\/pull.niues.live\/live\/stream-519740_lsd.m3u8?auth_key=1753295102-0-0-227fe19dccb3d06cc4a6fbdaf8887352",
                "referrer": "https:\/\/socolivev.co\/",
                "user_agent": ""
            },
            {
                "title": "Soco HD",
                "url": "https:\/\/pull.niues.live\/live\/stream-519740_lhd.m3u8?auth_key=1753295102-0-0-8aba1b474fde983f084a29502b5d34c3",
                "referrer": "https:\/\/socolivev.co\/",
                "user_agent": ""
            },
            {
                "title": "Soco SD",
                "url": "https:\/\/pull.niues.live\/live\/stream-344370_lsd.m3u8?auth_key=1753295500-0-0-2d7dd25b4dd8198618595773c41e7b97",
                "referrer": "https:\/\/socolivev.co\/",
                "user_agent": ""
            },
            {
                "title": "Soco HD",
                "url": "https:\/\/pull.niues.live\/live\/stream-344370_lhd.m3u8?auth_key=1753295500-0-0-c2e151881de1b80ff3084ea47aee967f",
                "referrer": "https:\/\/socolivev.co\/",
                "user_agent": ""
            },
            {
                "title": "Soco SD",
                "url": "https:\/\/pull.niues.live\/live\/stream-9912015_lsd.m3u8?auth_key=1753295247-0-0-6a99676ccc8777a6b40cb04cc95cd6e1",
                "referrer": "https:\/\/socolivev.co\/",
                "user_agent": ""
            },
            {
                "title": "Soco HD",
                "url": "https:\/\/pull.niues.live\/live\/stream-9912015_lhd.m3u8?auth_key=1753295247-0-0-5ff3eb3ca7ae5b9a50d7933d32b2c03a",
                "referrer": "https:\/\/socolivev.co\/",
                "user_agent": ""
            },
            {
                "title": "Soco SD",
                "url": "https:\/\/stream-flv.dfsfe.top\/lives\/9912060-480p.m3u8",
                "referrer": "https:\/\/socolivev.co\/",
                "user_agent": ""
            },
            {
                "title": "Soco HD",
                "url": "https:\/\/stream-flv.dfsfe.top\/lives\/9912060-720p.m3u8",
                "referrer": "https:\/\/socolivev.co\/",
                "user_agent": ""
            }
        ]
    },
    {
        "is_live": true,
        "date": "2025-07-23T15:30:00Z",
        "time": "",
        "id": "9912099",
        "logo": "",
        "home_team": "Finland Univ.",
        "home_image": "https:\/\/sta.vnres.co\/file\/common\/20250723\/e7ca53c9998295a58dd3098c5a4a76c9.png",
        "away_team": "USA Univ.",
        "away_image": "https:\/\/sta.vnres.co\/file\/common\/20250723\/126a6c6668403d585b4ae1dc0510185f.png",
        "league": "MWU BT",
        "links": [
            {
                "title": "Soco SD",
                "url": "https:\/\/pull.niur.live\/live\/stream-9912099_lsd.m3u8?txSecret=3724f78c79bd7bd683837bc27077599a&txTime=68816e96",
                "referrer": "https:\/\/socolivev.co\/",
                "user_agent": ""
            },
            {
                "title": "Soco HD",
                "url": "https:\/\/pull.niur.live\/live\/stream-9912099_lhd.m3u8?txSecret=4cfba52f8fb87fb67e92f54a535282a5&txTime=68816e96",
                "referrer": "https:\/\/socolivev.co\/",
                "user_agent": ""
            }
        ]
    },
    {
        "is_live": true,
        "date": "2025-07-23T18:30:00Z",
        "time": "",
        "id": "532081",
        "logo": "",
        "home_team": "Como",
        "home_image": "https:\/\/sta.vnres.co\/file\/common\/20250720\/84480520283185e980c8277760626250.png",
        "away_team": "Al-Ahli SFC",
        "away_image": "https:\/\/sta.vnres.co\/file\/common\/20250720\/a926fe1ad3c067ddcfb022ca2771c48d.png",
        "league": "INT CF",
        "links": [
            {
                "title": "Soco SD",
                "url": "https:\/\/pull.niues.live\/live\/stream-532081_lsd.m3u8?auth_key=1753306203-0-0-30769e77846178fa2da1ae20ecd3b640",
                "referrer": "https:\/\/socolivev.co\/",
                "user_agent": ""
            },
            {
                "title": "Soco HD",
                "url": "https:\/\/pull.niues.live\/live\/stream-532081_lhd.m3u8?auth_key=1753306203-0-0-0c8c7f5ca4e868abd058a4cb492883bb",
                "referrer": "https:\/\/socolivev.co\/",
                "user_agent": ""
            }
        ]
    },
    {
        "is_live": true,
        "date": "2025-07-23T18:45:00Z",
        "time": "",
        "id": "528758",
        "logo": "",
        "home_team": "Shelbourne",
        "home_image": "https:\/\/sta.vnres.co\/file\/common\/20250721\/c0c77711c87e9ad9e99a1e37239d6075.png",
        "away_team": "Qarabag",
        "away_image": "https:\/\/sta.vnres.co\/file\/common\/20250721\/d001b11583ed12b992cf4d2b17604476.png",
        "league": "UEFA CL",
        "links": [
            {
                "title": "Soco SD",
                "url": "https:\/\/pull.niues.live\/live\/stream-308080_lsd.m3u8?auth_key=1753306203-0-0-48b3136803e7f2285e57fcd1e3b601ee",
                "referrer": "https:\/\/socolivev.co\/",
                "user_agent": ""
            },
            {
                "title": "Soco HD",
                "url": "https:\/\/pull.niues.live\/live\/stream-308080_lhd.m3u8?auth_key=1753306203-0-0-6fc62b0dbbdacfd1cde84f9fc7925ec5",
                "referrer": "https:\/\/socolivev.co\/",
                "user_agent": ""
            },
            {
                "title": "Soco SD",
                "url": "https:\/\/pull.niues.live\/live\/stream-479849_lsd.m3u8?auth_key=1753306203-0-0-2c7f4ea72582d712918eb268441b63e8",
                "referrer": "https:\/\/socolivev.co\/",
                "user_agent": ""
            },
            {
                "title": "Soco HD",
                "url": "https:\/\/pull.niues.live\/live\/stream-479849_lhd.m3u8?auth_key=1753306203-0-0-be876bd1ce07194d53d141342c667c5e",
                "referrer": "https:\/\/socolivev.co\/",
                "user_agent": ""
            },
            {
                "title": "Soco SD",
                "url": "https:\/\/pull.niues.live\/live\/stream-9912097_lsd.m3u8?auth_key=1753306203-0-0-91ca100be3c5b0df7d9b57e63d149580",
                "referrer": "https:\/\/socolivev.co\/",
                "user_agent": ""
            },
            {
                "title": "Soco HD",
                "url": "https:\/\/pull.niues.live\/live\/stream-9912097_lhd.m3u8?auth_key=1753306203-0-0-71688215f7d62efc43ebf1fe0dabd1b6",
                "referrer": "https:\/\/socolivev.co\/",
                "user_agent": ""
            },
            {
                "title": "Soco SD",
                "url": "https:\/\/pull.niues.live\/live\/stream-484845_lsd.m3u8?auth_key=1753306203-0-0-34e82003f37e8e04f6dc80224d406ebe",
                "referrer": "https:\/\/socolivev.co\/",
                "user_agent": ""
            },
            {
                "title": "Soco HD",
                "url": "https:\/\/pull.niues.live\/live\/stream-484845_lhd.m3u8?auth_key=1753306203-0-0-5181d508da0030dd129bcefa0edbf30e",
                "referrer": "https:\/\/socolivev.co\/",
                "user_agent": ""
            },
            {
                "title": "Soco SD",
                "url": "https:\/\/pull.niues.live\/live\/stream-472241_lsd.m3u8?auth_key=1753306203-0-0-92eb330fc62ffb98ecffb28534c7a767",
                "referrer": "https:\/\/socolivev.co\/",
                "user_agent": ""
            },
            {
                "title": "Soco HD",
                "url": "https:\/\/pull.niues.live\/live\/stream-472241_lhd.m3u8?auth_key=1753306203-0-0-de684251c6375fbc43aff0a707216e88",
                "referrer": "https:\/\/socolivev.co\/",
                "user_agent": ""
            },
            {
                "title": "Soco SD",
                "url": "https:\/\/pull.niues.live\/live\/stream-528758_lsd.m3u8?auth_key=1753306203-0-0-e3fb018f42dfdca2ae56ca83eef84003",
                "referrer": "https:\/\/socolivev.co\/",
                "user_agent": ""
            },
            {
                "title": "Soco HD",
                "url": "https:\/\/pull.niues.live\/live\/stream-528758_lhd.m3u8?auth_key=1753306203-0-0-2feab7c92dc0a1b9a72b7f4b8a4f4784",
                "referrer": "https:\/\/socolivev.co\/",
                "user_agent": ""
            }
        ]
    },
    {
        "is_live": true,
        "date": "2025-07-23T18:45:00Z",
        "time": "",
        "id": "400722",
        "logo": "",
        "home_team": "Heart of Midlothian",
        "home_image": "https:\/\/sta.vnres.co\/file\/common\/20250721\/7a57b05b376902b6d70b2fc444ee6ed5.png",
        "away_team": "Dumbarton",
        "away_image": "https:\/\/sta.vnres.co\/file\/common\/20250721\/62feed844395341cb3f1b91af062552a.png",
        "league": "SCO LC",
        "links": [
            {
                "title": "Soco SD",
                "url": "https:\/\/pull.niues.live\/live\/stream-459401_lsd.m3u8?auth_key=1753306203-0-0-18d6361799149daf15d9f2a9c525ba2e",
                "referrer": "https:\/\/socolivev.co\/",
                "user_agent": ""
            },
            {
                "title": "Soco HD",
                "url": "https:\/\/pull.niues.live\/live\/stream-459401_lhd.m3u8?auth_key=1753306203-0-0-456928c7728e91f8cb2690c00b886a9e",
                "referrer": "https:\/\/socolivev.co\/",
                "user_agent": ""
            },
            {
                "title": "Soco SD",
                "url": "https:\/\/pull.niues.live\/live\/stream-400722_lsd.m3u8?auth_key=1753306203-0-0-37e209efbab3da76954906cbc6d528dd",
                "referrer": "https:\/\/socolivev.co\/",
                "user_agent": ""
            },
            {
                "title": "Soco HD",
                "url": "https:\/\/pull.niues.live\/live\/stream-400722_lhd.m3u8?auth_key=1753306203-0-0-d397564bfe90ef3e99d424104975cdbf",
                "referrer": "https:\/\/socolivev.co\/",
                "user_agent": ""
            }
        ]
    },
    {
        "is_live": true,
        "date": "2025-07-23T19:00:00Z",
        "time": "",
        "id": "512649",
        "logo": "",
        "home_team": "Fenerbahce",
        "home_image": "https:\/\/sta.vnres.co\/file\/common\/20250721\/62daf74c9fa6a6c996a6ececbc178372.png",
        "away_team": "Al-Ittihad Club",
        "away_image": "https:\/\/sta.vnres.co\/file\/common\/20250721\/ed6319a72286cb995aa6e39b84291723.png",
        "league": "INT CF",
        "links": [
            {
                "title": "Soco SD",
                "url": "https:\/\/pull.niues.live\/live\/stream-511367_lsd.m3u8?auth_key=1753306203-0-0-ff3a0d21f23cc9b7e0dd910503036b8d",
                "referrer": "https:\/\/socolivev.co\/",
                "user_agent": ""
            },
            {
                "title": "Soco HD",
                "url": "https:\/\/pull.niues.live\/live\/stream-511367_lhd.m3u8?auth_key=1753306203-0-0-3c97486abdfce90bbacf011f94b0fd6d",
                "referrer": "https:\/\/socolivev.co\/",
                "user_agent": ""
            },
            {
                "title": "Soco SD",
                "url": "https:\/\/pull.niues.live\/live\/stream-285067_lsd.m3u8?auth_key=1753306203-0-0-0034e9c1ed6118b7b6949c83f1944a49",
                "referrer": "https:\/\/socolivev.co\/",
                "user_agent": ""
            },
            {
                "title": "Soco HD",
                "url": "https:\/\/pull.niues.live\/live\/stream-285067_lhd.m3u8?auth_key=1753306203-0-0-a793b1b085f1199d600e45fd297e3470",
                "referrer": "https:\/\/socolivev.co\/",
                "user_agent": ""
            },
            {
                "title": "Soco SD",
                "url": "https:\/\/pull.niues.live\/live\/stream-406865_lsd.m3u8?auth_key=1753306203-0-0-948ba724a7b5fc3f3575fc470ac7e0a5",
                "referrer": "https:\/\/socolivev.co\/",
                "user_agent": ""
            },
            {
                "title": "Soco HD",
                "url": "https:\/\/pull.niues.live\/live\/stream-406865_lhd.m3u8?auth_key=1753306203-0-0-533ecb572bddc204d555a4560bcfbe7c",
                "referrer": "https:\/\/socolivev.co\/",
                "user_agent": ""
            },
            {
                "title": "Soco SD",
                "url": "https:\/\/pull.niues.live\/live\/stream-512649_lsd.m3u8?auth_key=1753306203-0-0-9de17fee02890c947211a1977f8ed1d2",
                "referrer": "https:\/\/socolivev.co\/",
                "user_agent": ""
            },
            {
                "title": "Soco HD",
                "url": "https:\/\/pull.niues.live\/live\/stream-512649_lhd.m3u8?auth_key=1753306203-0-0-c7efa52dd3a0d0160f56c70d74f6676f",
                "referrer": "https:\/\/socolivev.co\/",
                "user_agent": ""
            }
        ]
    },
    {
        "is_live": true,
        "date": "2025-07-23T19:00:00Z",
        "time": "",
        "id": "9912100",
        "logo": "",
        "home_team": "Germany Women",
        "home_image": "https:\/\/sta.vnres.co\/file\/common\/20250721\/04d1200a8500ec3ad1eefaeaca7a4812.png",
        "away_team": "Spain Women",
        "away_image": "https:\/\/sta.vnres.co\/file\/common\/20250721\/225aecee2832da5cf9343d33822b35f8.png",
        "league": "UEFACW",
        "links": [
            {
                "title": "Soco SD",
                "url": "https:\/\/pull.niues.live\/live\/stream-387694_lsd.m3u8?auth_key=1753306203-0-0-908d5a8593019dff7a62b2869f920f12",
                "referrer": "https:\/\/socolivev.co\/",
                "user_agent": ""
            },
            {
                "title": "Soco HD",
                "url": "https:\/\/pull.niues.live\/live\/stream-387694_lhd.m3u8?auth_key=1753306203-0-0-a9515320a4e8b0850a1f945e2a57bfb6",
                "referrer": "https:\/\/socolivev.co\/",
                "user_agent": ""
            },
            {
                "title": "Soco SD",
                "url": "https:\/\/pull.niues.live\/live\/stream-494201_lsd.m3u8?auth_key=1753306203-0-0-59e3757fc6306a2fc4c7aa8491ad3cd2",
                "referrer": "https:\/\/socolivev.co\/",
                "user_agent": ""
            },
            {
                "title": "Soco HD",
                "url": "https:\/\/pull.niues.live\/live\/stream-494201_lhd.m3u8?auth_key=1753306203-0-0-69fd3746255255c43d1ae7ddd59a1f56",
                "referrer": "https:\/\/socolivev.co\/",
                "user_agent": ""
            },
            {
                "title": "Soco SD",
                "url": "https:\/\/pull.niues.live\/live\/stream-9912110_lsd.m3u8?auth_key=1753306203-0-0-e65f7ef43f6963e0e6dd1a1a26f256ef",
                "referrer": "https:\/\/socolivev.co\/",
                "user_agent": ""
            },
            {
                "title": "Soco HD",
                "url": "https:\/\/pull.niues.live\/live\/stream-9912110_lhd.m3u8?auth_key=1753306203-0-0-0e4f38d6275de4cf47606f1a01b0dd13",
                "referrer": "https:\/\/socolivev.co\/",
                "user_agent": ""
            },
            {
                "title": "Soco SD",
                "url": "https:\/\/pull.niues.live\/live\/stream-327159_lsd.m3u8?auth_key=1753306203-0-0-782bddbd30e9955174d19b7dc7fb42af",
                "referrer": "https:\/\/socolivev.co\/",
                "user_agent": ""
            },
            {
                "title": "Soco HD",
                "url": "https:\/\/pull.niues.live\/live\/stream-327159_lhd.m3u8?auth_key=1753306203-0-0-a212f1e61c01b36c4a27b4b85c10f5b9",
                "referrer": "https:\/\/socolivev.co\/",
                "user_agent": ""
            },
            {
                "title": "Soco SD",
                "url": "https:\/\/pull.niues.live\/live\/stream-299144_lsd.m3u8?auth_key=1753306203-0-0-97df34dc9e9ea9970343bad53955b37f",
                "referrer": "https:\/\/socolivev.co\/",
                "user_agent": ""
            },
            {
                "title": "Soco HD",
                "url": "https:\/\/pull.niues.live\/live\/stream-299144_lhd.m3u8?auth_key=1753306203-0-0-3191a06fe18a9831f7dc24ef0a53cbd5",
                "referrer": "https:\/\/socolivev.co\/",
                "user_agent": ""
            },
            {
                "title": "Soco SD",
                "url": "https:\/\/pull.niues.live\/live\/stream-9912100_lsd.m3u8?auth_key=1753306203-0-0-8f4faa877ff5e4c2014c48b04399dd5c",
                "referrer": "https:\/\/socolivev.co\/",
                "user_agent": ""
            },
            {
                "title": "Soco HD",
                "url": "https:\/\/pull.niues.live\/live\/stream-9912100_lhd.m3u8?auth_key=1753306203-0-0-4657755884086d4badf0c41ce4fe219b",
                "referrer": "https:\/\/socolivev.co\/",
                "user_agent": ""
            }
        ]
    },
    {
        "is_live": false,
        "date": "2025-07-23T21:00:00Z",
        "time": "",
        "id": "9912100",
        "logo": "",
        "home_team": "Llaneros FC",
        "home_image": "https:\/\/sta.vnres.co\/file\/common\/20250721\/b1cc87fc4d2841f099ebcbfc299d860d.png",
        "away_team": "Boyaca Chico",
        "away_image": "https:\/\/sta.vnres.co\/file\/common\/20250721\/bf14a97bfc50f0b83b5a4ce3968a6e6e.png",
        "league": "COL D1",
        "links": []
    },
    {
        "is_live": false,
        "date": "2025-07-23T22:00:00Z",
        "time": "",
        "id": "9912100",
        "logo": "",
        "home_team": "Ceara",
        "home_image": "https:\/\/sta.vnres.co\/file\/common\/20250721\/7c3b25e3eb81e65287ea03b93cf5ea97.png",
        "away_team": "Mirassol",
        "away_image": "https:\/\/sta.vnres.co\/file\/common\/20250721\/dcd023aa11469dc5349543cf98be477b.png",
        "league": "BRA D1",
        "links": []
    },
    {
        "is_live": false,
        "date": "2025-07-23T22:00:00Z",
        "time": "",
        "id": "9912100",
        "logo": "",
        "home_team": "Fluminense RJ",
        "home_image": "https:\/\/sta.vnres.co\/file\/common\/20250721\/b7a33a84df58248a68e8940284c36964.png",
        "away_team": "Palmeiras",
        "away_image": "https:\/\/sta.vnres.co\/file\/common\/20250721\/7d86d1246f83c70ea8e8d8ca28b958dd.png",
        "league": "BRA D1",
        "links": []
    },
    {
        "is_live": false,
        "date": "2025-07-23T22:00:00Z",
        "time": "",
        "id": "9912100",
        "logo": "",
        "home_team": "Palestino",
        "home_image": "https:\/\/sta.vnres.co\/file\/common\/20250721\/c96c992c7d7aec4fc939c8e0bb5b7acc.png",
        "away_team": "Bolivar",
        "away_image": "https:\/\/sta.vnres.co\/file\/common\/20250721\/40fab5fda715ea8f9f4b39391eba9fad.png",
        "league": "CON CSA",
        "links": []
    },
    {
        "is_live": false,
        "date": "2025-07-23T22:30:00Z",
        "time": "",
        "id": "9912100",
        "logo": "",
        "home_team": "Corinthians Paulista (SP)",
        "home_image": "https:\/\/sta.vnres.co\/file\/common\/20250721\/bebc5fc6a8f2dfa4432715f40772ae2f.png",
        "away_team": "Cruzeiro Esporte Clube",
        "away_image": "https:\/\/sta.vnres.co\/file\/common\/20250721\/f213daf7855eb6b8033b0c8c50a171ba.png",
        "league": "BRA D1",
        "links": []
    },
    {
        "is_live": false,
        "date": "2025-07-23T23:10:00Z",
        "time": "",
        "id": "9912100",
        "logo": "",
        "home_team": "Atletico Junior Barranquilla",
        "home_image": "https:\/\/sta.vnres.co\/file\/common\/20250721\/8472a1c021d012874f52d4c0240e5a91.png",
        "away_team": "Union Magdalena",
        "away_image": "https:\/\/sta.vnres.co\/file\/common\/20250721\/714fd90c337aa7e9c4f7ef01231f0224.png",
        "league": "COL D1",
        "links": []
    },
    {
        "is_live": false,
        "date": "2025-07-24T00:00:00Z",
        "time": "",
        "id": "9912100",
        "logo": "",
        "home_team": "Indios",
        "home_image": "https:\/\/sta.vnres.co\/file\/common\/20250722\/8d170b6b26cdddb18cc06d700cdc00af.png",
        "away_team": "Metros de Santiago",
        "away_image": "https:\/\/sta.vnres.co\/file\/common\/20250722\/e668b8d2a58dec72048495c1481fa5da.png",
        "league": "DLNB",
        "links": []
    },
    {
        "is_live": false,
        "date": "2025-07-24T00:10:00Z",
        "time": "",
        "id": "9912100",
        "logo": "",
        "home_team": "Boca Juniors",
        "home_image": "https:\/\/sta.vnres.co\/file\/common\/20250721\/3fd1e3f4a269f42e4c907c50b2472f68.png",
        "away_team": "Atletico Tucuman",
        "away_image": "https:\/\/sta.vnres.co\/file\/common\/20250721\/e5cd8a5c0b00d0d4abd7be33ad8b9c29.png",
        "league": "ARG Cup",
        "links": []
    },
    {
        "is_live": false,
        "date": "2025-07-24T00:15:00Z",
        "time": "",
        "id": "9912100",
        "logo": "",
        "home_team": "Indios de Mayaguez",
        "home_image": "https:\/\/sta.vnres.co\/file\/common\/20250722\/8f35b091382fc2b9000562a2198589f7.png",
        "away_team": "Leones De Ponce",
        "away_image": "https:\/\/sta.vnres.co\/file\/common\/20250722\/3c37613744577153d074506c2c41fc4c.png",
        "league": "BSN",
        "links": []
    },
    {
        "is_live": false,
        "date": "2025-07-24T00:30:00Z",
        "time": "",
        "id": "9912100",
        "logo": "",
        "home_team": "Red Bull Bragantino",
        "home_image": "https:\/\/sta.vnres.co\/file\/common\/20250721\/341e2810df325c76be2d01a095817373.png",
        "away_team": "CR Flamengo",
        "away_image": "https:\/\/sta.vnres.co\/file\/common\/20250721\/a2529ce982c92ffcda8f75257b95f416.png",
        "league": "BRA D1",
        "links": []
    },
    {
        "is_live": false,
        "date": "2025-07-24T00:30:00Z",
        "time": "",
        "id": "9912100",
        "logo": "",
        "home_team": "Santos",
        "home_image": "https:\/\/sta.vnres.co\/file\/common\/20250721\/30774e46724c9d835030ecad137e1225.png",
        "away_team": "Internacional RS",
        "away_image": "https:\/\/sta.vnres.co\/file\/common\/20250721\/e6871ffdce5354d3d4c1cb1371f397a1.png",
        "league": "BRA D1",
        "links": []
    },
    {
        "is_live": false,
        "date": "2025-07-24T00:30:00Z",
        "time": "",
        "id": "9912100",
        "logo": "",
        "home_team": "Vitoria BA",
        "home_image": "https:\/\/sta.vnres.co\/file\/common\/20250721\/75166979279651c8e9c69530fbbc0265.png",
        "away_team": "Sport Club do Recife",
        "away_image": "https:\/\/sta.vnres.co\/file\/common\/20250721\/467e6c6f74c3bfc375c905efa3bcdd11.png",
        "league": "BRA D1",
        "links": []
    },
    {
        "is_live": false,
        "date": "2025-07-24T00:30:00Z",
        "time": "",
        "id": "9912100",
        "logo": "",
        "home_team": "Gremio (RS)",
        "home_image": "https:\/\/sta.vnres.co\/file\/common\/20250721\/3c5cb1698b3f9db1b0c70c0dfc1c28fb.png",
        "away_team": "Alianza Lima",
        "away_image": "https:\/\/sta.vnres.co\/file\/common\/20250721\/4af7622a515540565efad7ea135a4509.png",
        "league": "CON CSA",
        "links": []
    },
    {
        "is_live": false,
        "date": "2025-07-24T00:30:00Z",
        "time": "",
        "id": "9912100",
        "logo": "",
        "home_team": "Deportiva Once Caldas",
        "home_image": "https:\/\/sta.vnres.co\/file\/common\/20250721\/092a4913c051234e59114e8bb742c975.png",
        "away_team": "San Antonio Bulo Bulo",
        "away_image": "https:\/\/sta.vnres.co\/file\/common\/20250721\/883a18613fcf7b0f075855b95b6f15d5.png",
        "league": "CON CSA",
        "links": []
    },
    {
        "is_live": false,
        "date": "2025-07-24T01:00:00Z",
        "time": "",
        "id": "9912100",
        "logo": "",
        "home_team": "MLS All-Stars",
        "home_image": "https:\/\/sta.vnres.co\/file\/common\/20250721\/a988133486144c6b956c708c4b5e0520.png",
        "away_team": "Mexico All Stars",
        "away_image": "https:\/\/sta.vnres.co\/file\/common\/20250721\/72c6b81aee7d312db3e2cb8e3aa46b44.png",
        "league": "INT CF",
        "links": []
    },
    {
        "is_live": false,
        "date": "2025-07-24T01:20:00Z",
        "time": "",
        "id": "9912100",
        "logo": "",
        "home_team": "La Equidad",
        "home_image": "https:\/\/sta.vnres.co\/file\/common\/20250721\/75b82d09995a97ad5052d680b7b049d5.png",
        "away_team": "Millonarios",
        "away_image": "https:\/\/sta.vnres.co\/file\/common\/20250721\/a9b911aca509414584f565f79f2e8923.png",
        "league": "COL D1",
        "links": []
    },
    {
        "is_live": false,
        "date": "2025-07-24T02:00:00Z",
        "time": "",
        "id": "9912100",
        "logo": "",
        "home_team": "Halcones de Xalapa",
        "home_image": "https:\/\/sta.vnres.co\/file\/common\/20250722\/ec9009e02ef6cef7b329efbe33fb6d51.png",
        "away_team": "Gambusinos",
        "away_image": "https:\/\/sta.vnres.co\/file\/common\/20250722\/19e2815b0de81d4c31050a91ccbef848.png",
        "league": "LNBP",
        "links": []
    },
    {
        "is_live": false,
        "date": "2025-07-24T02:00:00Z",
        "time": "",
        "id": "9912100",
        "logo": "",
        "home_team": "Soles",
        "home_image": "https:\/\/sta.vnres.co\/file\/common\/20250722\/5aa544fe0cb12bef2f740f4ce197e0d2.png",
        "away_team": "Correcaminos",
        "away_image": "https:\/\/sta.vnres.co\/file\/common\/20250722\/3f9caae96d3c8e9481c95fbaa7dc9a2c.png",
        "league": "LNBP",
        "links": []
    },
    {
        "is_live": false,
        "date": "2025-07-24T02:00:00Z",
        "time": "",
        "id": "9912100",
        "logo": "",
        "home_team": "Phoenix Mercury W",
        "home_image": "https:\/\/sta.vnres.co\/file\/common\/20250722\/164f18a0f1c06ac6b01578d6606121c8.png",
        "away_team": "Atlanta Dream W",
        "away_image": "https:\/\/sta.vnres.co\/file\/common\/20250722\/216d97f9b57797a6fe594f12a5319d47.png",
        "league": "WNBA",
        "links": []
    },
    {
        "is_live": false,
        "date": "2025-07-24T08:30:00Z",
        "time": "",
        "id": "9912100",
        "logo": "",
        "home_team": "Dong Thap U21",
        "home_image": "https:\/\/sta.vnres.co\/file\/common\/20250721\/fdc3988f80504d97fe9c8faeded0a69c.png",
        "away_team": "Dak Lak U21",
        "away_image": "https:\/\/sta.vnres.co\/file\/common\/20250721\/b0d450f923ad78df7e5560e64bccde5b.png",
        "league": "VIE U21",
        "links": []
    },
    {
        "is_live": false,
        "date": "2025-07-24T10:00:00Z",
        "time": "",
        "id": "9912100",
        "logo": "",
        "home_team": "FK Aktobe II",
        "home_image": "https:\/\/sta.vnres.co\/file\/common\/20250721\/6f34a1583236db5500aea898fbda32f3.png",
        "away_team": "Ekibastuzets",
        "away_image": "https:\/\/sta.vnres.co\/file\/common\/20250721\/582b65ea216a97d708db9bb6e746e4f0.png",
        "league": "KAZ D1",
        "links": []
    },
    {
        "is_live": false,
        "date": "2025-07-24T10:00:00Z",
        "time": "",
        "id": "9912100",
        "logo": "",
        "home_team": "Samtse",
        "home_image": "https:\/\/sta.vnres.co\/file\/common\/20250723\/d1bc0b6a4e7db9a0969907530ee92cdf.png",
        "away_team": "Paro",
        "away_image": "https:\/\/sta.vnres.co\/file\/common\/20250723\/6a7e6f038a88c04261039adae2f99509.png",
        "league": "BHU SL",
        "links": []
    },
    {
        "is_live": false,
        "date": "2025-07-24T12:00:00Z",
        "time": "",
        "id": "9912100",
        "logo": "",
        "home_team": "Akademiya Ontustik",
        "home_image": "https:\/\/sta.vnres.co\/file\/common\/20250721\/bcc5ce3a1511e3d3e3e244614183b8f4.png",
        "away_team": "FK Kaspyi Aktau",
        "away_image": "https:\/\/sta.vnres.co\/file\/common\/20250721\/cf5123c7d52d8165304e874ebfa2f9a2.png",
        "league": "KAZ D1",
        "links": []
    },
    {
        "is_live": false,
        "date": "2025-07-24T12:00:00Z",
        "time": "",
        "id": "9912100",
        "logo": "",
        "home_team": "Kairat Almaty II",
        "home_image": "https:\/\/sta.vnres.co\/file\/common\/20250721\/44531625484cbcdcb4f6ba9df02b6fd4.png",
        "away_team": "Irtysh Pavlodar",
        "away_image": "https:\/\/sta.vnres.co\/file\/common\/20250721\/e615956eed569cacd072e9199a4856aa.png",
        "league": "KAZ D1",
        "links": []
    },
    {
        "is_live": false,
        "date": "2025-07-24T12:30:00Z",
        "time": "",
        "id": "9912100",
        "logo": "",
        "home_team": "Nhatrang Dolphins",
        "home_image": "https:\/\/sta.vnres.co\/file\/common\/20250722\/de20af764f1c727a813c7ed5eb473a75.png",
        "away_team": "Ho Chi Minh City Wings",
        "away_image": "https:\/\/sta.vnres.co\/file\/common\/20250722\/fa7fce29d1040f347da45c978ca73f1c.png",
        "league": "VBA",
        "links": []
    },
    {
        "is_live": false,
        "date": "2025-07-24T14:00:00Z",
        "time": "",
        "id": "9912100",
        "logo": "",
        "home_team": "FC Astana",
        "home_image": "https:\/\/sta.vnres.co\/file\/common\/20250721\/95b297324ff60010011a29de8e148af5.png",
        "away_team": "Zimbru Chisinau",
        "away_image": "https:\/\/sta.vnres.co\/file\/common\/20250721\/0c82b6e568438d1e0f3cf0ae893ab789.png",
        "league": "UEFA ECL",
        "links": []
    }
]